{"components_accordion.md":"Dgwi64Hc","components_alert.md":"BdMq4LRf","components_aspect-ratio.md":"DfxQSYXV","components_avatar.md":"B9llwEdV","components_badge-fx.md":"ND8U3i28","components_badge.md":"fxl6My_0","components_breadcrumb.md":"DG1_QVDu","components_button-fx.md":"Bp3TpXvX","components_button.md":"BK4Ee4X_","components_card.md":"D5ngIjwn","components_checkbox.md":"BFXyywDI","components_collapsible.md":"BHAVgr38","components_combobox.md":"DJOFk1kf","components_copybutton.md":"BbWO3nt8","components_dialog.md":"DndrDCVi","components_divider.md":"TJHag80S","components_drawer.md":"RqQyB6wT","components_empty-state.md":"B7k4cBu3","components_fieldset.md":"CfOVOkUQ","components_flex.md":"BTDRjfdy","components_header.md":"KC4J6jHa","components_icon-button-fx.md":"D3kR6Uvf","components_icon-button.md":"CHugdBMS","components_icon.md":"vfGu5Ge0","components_image.md":"3TObOUYO","components_input.md":"DBjaj9Se","components_intl-formatter.md":"Do8qpfZf","components_kbd.md":"DHX8gG8a","components_link.md":"D8gn6jD-","components_loader.md":"Be-iuy4v","components_mark.md":"Cb8zy8dF","components_menu.md":"Caxzqduj","components_message-bubble.md":"BqYlD75Q","components_pagination.md":"CbpPe2Bk","components_popover.md":"KX4LzJf_","components_progress-ring.md":"BoKAU0eO","components_progress.md":"BhRFdIzz","components_radio.md":"Cyi06_1P","components_rating.md":"CDRc1DHN","components_scroll-progress.md":"DdRetDeE","components_scroll-to-button.md":"B8PJMkj7","components_select.md":"cdW4FSPt","components_selection-button-group.md":"X3Mb-4h9","components_selection-card-group.md":"DbkxE14k","components_sidebar.md":"NTGKfbVV","components_skeleton-loader.md":"De6HJQZH","components_slider.md":"CWGrxjgo","components_spinner.md":"JyKDl3qB","components_table.md":"D5nmTIUu","components_tabs.md":"iIZEcBFm","components_tag.md":"CfdMBRG_","components_timeline.md":"BRxOat-T","components_toast.md":"CAxLA3KM","components_toggle.md":"Je482R6h","components_tooltip.md":"Dd4m2voI","components_visually-hidden.md":"CnRriZQh","docs_advanced_advanced-usage.md":"MZhHG-bY","docs_faq.md":"BfdkUYA1","docs_form-association.md":"Bzb5AMLa","docs_setup.md":"B3OT0Qbc","docs_theming.md":"BXTGXMBI","docs_understand.md":"CB1Zs0Fj","docs_utilities.md":"D1m5i7gG","index.md":"DRNQGVx2","installation.md":"DQaUfdTz","playbooks_blog.md":"BAQwr2EQ","playbooks_dashboard.md":"DtI5DV5r","playbooks_form-association.md":"VMbezalR","playbooks_grid.md":"DItbbux7","playbooks_landing.md":"BhK7srOP","playbooks_login.md":"BKV22Gxv","playbooks_onboarding.md":"CGPSJtza","playbooks_support.md":"BKXlyRTy","theming.md":"C2NhNsVb"}
